<?xml version="1.0" encoding="UTF-8"?><record_update table="sp_instance">
    <sp_instance action="DELETE">
        <active>true</active>
        <class_name/>
        <color>default</color>
        <css/>
        <glyph/>
        <id/>
        <order>2</order>
        <roles/>
        <short_description/>
        <size>md</size>
        <sp_column display_value="2">f58fee3f834e6e10216cf7a6feaad3f0</sp_column>
        <sp_widget display_value="Test Context">07087c30ff223100ba13ffffffffff08</sp_widget>
        <sys_class_name>sp_instance</sys_class_name>
        <sys_created_by>admin</sys_created_by>
        <sys_created_on>2025-06-17 17:40:59</sys_created_on>
        <sys_id>97c6c4c48316ae10216cf7a6feaad352</sys_id>
        <sys_mod_count>0</sys_mod_count>
        <sys_name/>
        <sys_package display_value="Leave Request Management" source="x_1777187_leave_0">8484ac5d83ce2210216cf7a6feaad358</sys_package>
        <sys_policy/>
        <sys_scope display_value="Leave Request Management">8484ac5d83ce2210216cf7a6feaad358</sys_scope>
        <sys_update_name>sp_instance_97c6c4c48316ae10216cf7a6feaad352</sys_update_name>
        <sys_updated_by>admin</sys_updated_by>
        <sys_updated_on>2025-06-17 17:40:59</sys_updated_on>
        <title/>
        <url/>
        <widget_parameters/>
    </sp_instance>
    <sys_translated_text action="DELETE" query="documentkey=97c6c4c48316ae10216cf7a6feaad352"/>
    <sys_update_version action="INSERT_OR_UPDATE">
        <action>DELETE</action>
        <application display_value="Leave Request Management">8484ac5d83ce2210216cf7a6feaad358</application>
        <file_path/>
        <instance_id>b0f3844eeb702e5056eafddacad0cd6a</instance_id>
        <instance_name>dev324208</instance_name>
        <name>sp_instance_97c6c4c48316ae10216cf7a6feaad352</name>
        <payload><![CDATA[<?xml version="1.0" encoding="UTF-8"?><record_update table="sp_instance"><sp_instance action="INSERT_OR_UPDATE"><active>true</active><class_name/><color>default</color><css/><glyph/><id/><order>2</order><roles/><short_description/><size>md</size><sp_column display_value="2">f58fee3f834e6e10216cf7a6feaad3f0</sp_column><sp_widget display_value="Test Context">07087c30ff223100ba13ffffffffff08</sp_widget><sys_class_name>sp_instance</sys_class_name><sys_created_by>admin</sys_created_by><sys_created_on>2025-06-17 17:40:59</sys_created_on><sys_id>97c6c4c48316ae10216cf7a6feaad352</sys_id><sys_mod_count>0</sys_mod_count><sys_name/><sys_package display_value="Leave Request Management" source="x_1777187_leave_0">8484ac5d83ce2210216cf7a6feaad358</sys_package><sys_policy/><sys_scope display_value="Leave Request Management">8484ac5d83ce2210216cf7a6feaad358</sys_scope><sys_update_name>sp_instance_97c6c4c48316ae10216cf7a6feaad352</sys_update_name><sys_updated_by>admin</sys_updated_by><sys_updated_on>2025-06-17 17:40:59</sys_updated_on><title/><url/><widget_parameters/></sp_instance><sys_translated_text action="delete_multiple" query="documentkey=97c6c4c48316ae10216cf7a6feaad352"/></record_update>]]></payload>
        <payload_hash>1041922074</payload_hash>
        <record_name/>
        <reverted_from/>
        <source>9a78553f83866e10216cf7a6feaad36f</source>
        <source_table>sys_update_set</source_table>
        <state>previous</state>
        <sys_created_by>admin</sys_created_by>
        <sys_created_on>2025-06-17 17:40:59</sys_created_on>
        <sys_id>27c6c4c48316ae10216cf7a6feaad355</sys_id>
        <sys_mod_count>0</sys_mod_count>
        <sys_recorded_at>1977efade850000001</sys_recorded_at>
        <sys_updated_by>admin</sys_updated_by>
        <sys_updated_on>2025-06-17 17:40:59</sys_updated_on>
        <type>Instance</type>
        <update_guid>2bc6c4c46416ae10230f81967b2c9554</update_guid>
        <update_guid_history>2bc6c4c46416ae10230f81967b2c9554:1041922074</update_guid_history>
    </sys_update_version>
    <sys_metadata_delete action="INSERT_OR_UPDATE">
        <sys_audit_delete display_value="">bc970c088316ae10216cf7a6feaad387</sys_audit_delete>
        <sys_class_name>sys_metadata_delete</sys_class_name>
        <sys_created_by>admin</sys_created_by>
        <sys_created_on>2025-06-17 17:44:22</sys_created_on>
        <sys_db_object display_value="" name="sp_instance">sp_instance</sys_db_object>
        <sys_id>01a32bff706a4584800c43c67b6b8c31</sys_id>
        <sys_metadata>97c6c4c48316ae10216cf7a6feaad352</sys_metadata>
        <sys_mod_count>0</sys_mod_count>
        <sys_name/>
        <sys_package display_value="Leave Request Management" source="x_1777187_leave_0">8484ac5d83ce2210216cf7a6feaad358</sys_package>
        <sys_parent/>
        <sys_policy/>
        <sys_scope display_value="Leave Request Management">8484ac5d83ce2210216cf7a6feaad358</sys_scope>
        <sys_scope_delete display_value="">7c9cbf7cdfd847108f9b129e6c6ff8e4</sys_scope_delete>
        <sys_update_name>sp_instance_97c6c4c48316ae10216cf7a6feaad352</sys_update_name>
        <sys_update_version display_value="sp_instance_97c6c4c48316ae10216cf7a6feaad352">27c6c4c48316ae10216cf7a6feaad355</sys_update_version>
        <sys_updated_by>admin</sys_updated_by>
        <sys_updated_on>2025-06-17 17:44:22</sys_updated_on>
    </sys_metadata_delete>
</record_update>
